INSTALL.txt
LICENSE.txt
MANIFEST.in
README.rst
setup.py
typogrify/__init__.py
typogrify/filters.py
typogrify/templatetags/__init__.py
typogrify/templatetags/jinja_filters.py
typogrify/templatetags/typogrify_tags.py
typogrify_engineer.egg-info/PKG-INFO
typogrify_engineer.egg-info/SOURCES.txt
typogrify_engineer.egg-info/dependency_links.txt
typogrify_engineer.egg-info/requires.txt
typogrify_engineer.egg-info/top_level.txt