Metadata-Version: 1.1
Name: typogrify-engineer
Version: 2.0.0
Summary: Typography related template filters for Django & Jinja2 applications
Home-page: https://github.com/mintchaos/typogrify
Author: Christian Metts
Author-email: xian@mintchaos.com
License: BSD
Platform: UNKNOWN
Classifier: Development Status :: 5 - Production/Stable
Classifier: Environment :: Web Environment
Classifier: Intended Audience :: Developers
Classifier: License :: OSI Approved :: BSD License
Classifier: Operating System :: OS Independent
Classifier: Programming Language :: Python
Classifier: Framework :: Django
Classifier: Topic :: Utilities
